{
  "meta": {
    "updated": 1783906731,
    "sources": [
      {
        "source": "大分県 食品営業許可施設一覧",
        "license": "Creative Commons Attribution 4.0 International"
      },
      {
        "source": "大分市食品営業許可・届出施設一覧",
        "license": "CC BY 2.1 JP"
      },
      {
        "source": "厚生労働省 食品衛生申請等システム（オープンデータ）",
        "license": "公共データ利用規約（第1.0版, PDL1.0）"
      }
    ]
  },
  "data": {
    "由布市": 1051,
    "九重町": 272,
    "日田市": 1330,
    "宇佐市": 978,
    "中津市": 1671,
    "国東市": 484,
    "臼杵市": 588,
    "別府市": 2565,
    "津久見市": 237,
    "豊後高田市": 426,
    "佐伯市": 1321,
    "竹田市": 507,
    "豊後大野市": 527,
    "玖珠町": 349,
    "杵築市": 418,
    "姫島村": 45,
    "日出町": 330,
    "不明": 906,
    "大分市": 7002,
    "玖珠郡九重町": 19,
    "玖珠郡玖珠町": 33,
    "速見郡日出町": 27
  }
}
