{
  "meta": {
    "updated": 1783906731,
    "sources": [
      {
        "source": "富山県食品営業許可施設一覧",
        "license": "CC BY"
      }
    ]
  },
  "data": [
    {
      "name": "魚津港直行便",
      "name_kana": "",
      "business_type": "飲食店営業",
      "address": "富山県内一円",
      "lat": null,
      "lng": null,
      "geocoding_level": null,
      "phone": "",
      "license_no": "120306",
      "license_date": null,
      "expire_date": null
    },
    {
      "name": "たこ焼　くろ舟",
      "name_kana": "",
      "business_type": "飲食店営業",
      "address": "県内一円",
      "lat": null,
      "lng": null,
      "geocoding_level": null,
      "phone": "",
      "license_no": "120747",
      "license_date": null,
      "expire_date": null
    },
    {
      "name": "どんどん焼本舗小幡",
      "name_kana": "",
      "business_type": "飲食店営業",
      "address": "富山県下一円",
      "lat": null,
      "lng": null,
      "geocoding_level": null,
      "phone": "",
      "license_no": "130702",
      "license_date": null,
      "expire_date": null
    },
    {
      "name": "居酒屋ゆーらっぷ",
      "name_kana": "",
      "business_type": "飲食店営業",
      "address": "富山県内一円",
      "lat": null,
      "lng": null,
      "geocoding_level": null,
      "phone": "0765-57-1400",
      "license_no": "170451",
      "license_date": null,
      "expire_date": null
    },
    {
      "name": "セブンイレブン安心お届け便",
      "name_kana": "",
      "business_type": "乳類販売業",
      "address": "県内一円",
      "lat": null,
      "lng": null,
      "geocoding_level": null,
      "phone": "",
      "license_no": "180018",
      "license_date": null,
      "expire_date": null
    },
    {
      "name": "セブンイレブン黒部三日市店",
      "name_kana": "",
      "business_type": "その他の食料・飲料販売業",
      "address": "富山県内一円",
      "lat": null,
      "lng": null,
      "geocoding_level": null,
      "phone": "0765-54-1234",
      "license_no": "180137",
      "license_date": null,
      "expire_date": null
    },
    {
      "name": "キッチン　Ｂ・Ｂ・Ｂ",
      "name_kana": "",
      "business_type": "飲食店営業",
      "address": "富山県内一円",
      "lat": null,
      "lng": null,
      "geocoding_level": null,
      "phone": "",
      "license_no": "180264",
      "license_date": null,
      "expire_date": null
    },
    {
      "name": "Ｍ’ｓＯｎｅ",
      "name_kana": "",
      "business_type": "飲食店営業",
      "address": "県内一円",
      "lat": null,
      "lng": null,
      "geocoding_level": null,
      "phone": "",
      "license_no": "190262",
      "license_date": null,
      "expire_date": null
    },
    {
      "name": "株式会社　新田由商店",
      "name_kana": "",
      "business_type": "魚介類販売業（包装済の魚介類のみの販売）",
      "address": "富山県内一円",
      "lat": null,
      "lng": null,
      "geocoding_level": null,
      "phone": "",
      "license_no": "190658",
      "license_date": null,
      "expire_date": null
    },
    {
      "name": "ROUTE18",
      "name_kana": "",
      "business_type": "飲食店営業",
      "address": "富山県内一円　金沢830　た　・・18",
      "lat": null,
      "lng": null,
      "geocoding_level": null,
      "phone": "",
      "license_no": "200125",
      "license_date": null,
      "expire_date": null
    },
    {
      "name": "キッチン　オリーブ",
      "name_kana": "",
      "business_type": "飲食店営業",
      "address": "富山県内一円",
      "lat": null,
      "lng": null,
      "geocoding_level": null,
      "phone": "",
      "license_no": "200466",
      "license_date": null,
      "expire_date": null
    },
    {
      "name": "やたい劇場",
      "name_kana": "",
      "business_type": "飲食店営業",
      "address": "富山県内一円",
      "lat": null,
      "lng": null,
      "geocoding_level": null,
      "phone": "",
      "license_no": "200471",
      "license_date": null,
      "expire_date": null
    },
    {
      "name": "あぶり肉がらん",
      "name_kana": "",
      "business_type": "飲食店営業",
      "address": "富山県一円",
      "lat": null,
      "lng": null,
      "geocoding_level": null,
      "phone": "",
      "license_no": "200589",
      "license_date": null,
      "expire_date": null
    },
    {
      "name": "Tarteta",
      "name_kana": "",
      "business_type": "飲食店営業",
      "address": "富山県内一円",
      "lat": null,
      "lng": null,
      "geocoding_level": null,
      "phone": "",
      "license_no": "210055",
      "license_date": null,
      "expire_date": null
    },
    {
      "name": "鮮魚前商店",
      "name_kana": "",
      "business_type": "魚介類販売業（包装済の魚介類のみの販売）",
      "address": "富山県下一円",
      "lat": null,
      "lng": null,
      "geocoding_level": null,
      "phone": "",
      "license_no": "210149",
      "license_date": null,
      "expire_date": null
    },
    {
      "name": "Ken's Food Truck",
      "name_kana": "",
      "business_type": "飲食店営業",
      "address": "富山県内一円",
      "lat": null,
      "lng": null,
      "geocoding_level": null,
      "phone": "",
      "license_no": "210197",
      "license_date": null,
      "expire_date": null
    },
    {
      "name": "竜鳳・宇都宮　４号車",
      "name_kana": "",
      "business_type": "飲食店営業",
      "address": "富山県内一円",
      "lat": null,
      "lng": null,
      "geocoding_level": null,
      "phone": "076-225-3142",
      "license_no": "210273",
      "license_date": null,
      "expire_date": null
    },
    {
      "name": "宝商店マカ号",
      "name_kana": "",
      "business_type": "飲食店営業",
      "address": "富山県内一円",
      "lat": null,
      "lng": null,
      "geocoding_level": null,
      "phone": "",
      "license_no": "210308",
      "license_date": null,
      "expire_date": null
    },
    {
      "name": "ＦＵＮコレフードコート",
      "name_kana": "",
      "business_type": "飲食店営業",
      "address": "富山県内一円",
      "lat": null,
      "lng": null,
      "geocoding_level": null,
      "phone": "",
      "license_no": "210436",
      "license_date": null,
      "expire_date": null
    },
    {
      "name": "ＢＩＧＵＰ　ＪＡＰＡＮ",
      "name_kana": "",
      "business_type": "飲食店営業",
      "address": "大阪府枚方市渚西1-12 富山県内一円",
      "lat": null,
      "lng": null,
      "geocoding_level": null,
      "phone": "",
      "license_no": "210442",
      "license_date": null,
      "expire_date": null
    },
    {
      "name": "アクアキッチン　バンビ",
      "name_kana": "",
      "business_type": "飲食店営業",
      "address": "富山県一円",
      "lat": null,
      "lng": null,
      "geocoding_level": null,
      "phone": "",
      "license_no": "210455",
      "license_date": null,
      "expire_date": null
    },
    {
      "name": "竜鳳・宇都宮　６号車",
      "name_kana": "",
      "business_type": "飲食店営業",
      "address": "金沢市森戸1－106　宇都宮880あ1771 富山県内一円",
      "lat": null,
      "lng": null,
      "geocoding_level": null,
      "phone": "076-225-3142",
      "license_no": "210457",
      "license_date": null,
      "expire_date": null
    },
    {
      "name": "俺の生ブリュレ",
      "name_kana": "",
      "business_type": "飲食店営業",
      "address": "富山県一円",
      "lat": null,
      "lng": null,
      "geocoding_level": null,
      "phone": "",
      "license_no": "210487",
      "license_date": null,
      "expire_date": null
    },
    {
      "name": "串焼　匠",
      "name_kana": "",
      "business_type": "飲食店営業",
      "address": "富山県一円",
      "lat": null,
      "lng": null,
      "geocoding_level": null,
      "phone": "",
      "license_no": "210696",
      "license_date": null,
      "expire_date": null
    },
    {
      "name": "酒馳走こころ１号",
      "name_kana": "",
      "business_type": "飲食店営業",
      "address": "京都府宇治市槇島町三十五56-14 富山県内一円",
      "lat": null,
      "lng": null,
      "geocoding_level": null,
      "phone": "",
      "license_no": "210746",
      "license_date": null,
      "expire_date": null
    },
    {
      "name": "酒馳走こころ２号",
      "name_kana": "",
      "business_type": "飲食店営業",
      "address": "京都府宇治市槇島町三十五56-14 富山県内一円",
      "lat": null,
      "lng": null,
      "geocoding_level": null,
      "phone": "0766-32-1100",
      "license_no": "210747",
      "license_date": null,
      "expire_date": null
    },
    {
      "name": "＃おやたま",
      "name_kana": "",
      "business_type": "飲食店営業",
      "address": "富山県内一円",
      "lat": null,
      "lng": null,
      "geocoding_level": null,
      "phone": "",
      "license_no": "210767",
      "license_date": null,
      "expire_date": null
    },
    {
      "name": "ｂ－らいふ　フードトラック　1号車",
      "name_kana": "",
      "business_type": "飲食店営業",
      "address": "富山県内一円",
      "lat": null,
      "lng": null,
      "geocoding_level": null,
      "phone": "",
      "license_no": "210801",
      "license_date": null,
      "expire_date": null
    },
    {
      "name": "宝商店マカ号２",
      "name_kana": "",
      "business_type": "飲食店営業",
      "address": "富山県一円",
      "lat": null,
      "lng": null,
      "geocoding_level": null,
      "phone": "",
      "license_no": "210994",
      "license_date": null,
      "expire_date": null
    },
    {
      "name": "カリガリカレー",
      "name_kana": "",
      "business_type": "飲食店営業",
      "address": "富山県一円",
      "lat": null,
      "lng": null,
      "geocoding_level": null,
      "phone": "",
      "license_no": "211063",
      "license_date": null,
      "expire_date": null
    },
    {
      "name": "飛天龍",
      "name_kana": "",
      "business_type": "飲食店営業",
      "address": "富山県内一円 前：金沢300の3462　後：金沢800る・148",
      "lat": null,
      "lng": null,
      "geocoding_level": null,
      "phone": "076-291-4828",
      "license_no": "221044",
      "license_date": null,
      "expire_date": null
    },
    {
      "name": "ドリームキッチンカー",
      "name_kana": "",
      "business_type": "飲食店営業",
      "address": "富山県内一円",
      "lat": null,
      "lng": null,
      "geocoding_level": null,
      "phone": "",
      "license_no": "221107",
      "license_date": null,
      "expire_date": null
    },
    {
      "name": "Ｓｗｅｅｔｓ　ＨＥＲＯ",
      "name_kana": "",
      "business_type": "飲食店営業",
      "address": "富山県内一円",
      "lat": null,
      "lng": null,
      "geocoding_level": null,
      "phone": "",
      "license_no": "221142",
      "license_date": null,
      "expire_date": null
    },
    {
      "name": "Aコープ移動購買者",
      "name_kana": "",
      "business_type": "百貨店、総合スーパー",
      "address": "富山県内一円",
      "lat": null,
      "lng": null,
      "geocoding_level": null,
      "phone": "0763-62-8811",
      "license_no": "221172",
      "license_date": null,
      "expire_date": null
    },
    {
      "name": "HAL・HAL",
      "name_kana": "",
      "business_type": "飲食店営業",
      "address": "石川県金沢市彦三町2丁目1－10　真和ビルB1F 富山県内一円　金沢800あ708",
      "lat": null,
      "lng": null,
      "geocoding_level": null,
      "phone": "076-256-0337",
      "license_no": "221331",
      "license_date": null,
      "expire_date": null
    },
    {
      "name": "からてん",
      "name_kana": "",
      "business_type": "飲食店営業",
      "address": "富山県内一円",
      "lat": null,
      "lng": null,
      "geocoding_level": null,
      "phone": "",
      "license_no": "221466",
      "license_date": null,
      "expire_date": null
    },
    {
      "name": "Burger Maps",
      "name_kana": "",
      "business_type": "飲食店営業",
      "address": "富山県内一円 金沢100さ7399",
      "lat": null,
      "lng": null,
      "geocoding_level": null,
      "phone": "",
      "license_no": "221593",
      "license_date": null,
      "expire_date": null
    },
    {
      "name": "美ら島の葉菜",
      "name_kana": "",
      "business_type": "飲食店営業",
      "address": "富山県内一円",
      "lat": null,
      "lng": null,
      "geocoding_level": null,
      "phone": "",
      "license_no": "221614",
      "license_date": null,
      "expire_date": null
    },
    {
      "name": "鯛平楽",
      "name_kana": "",
      "business_type": "飲食店営業",
      "address": "富山県内一円",
      "lat": null,
      "lng": null,
      "geocoding_level": null,
      "phone": "",
      "license_no": "221659",
      "license_date": null,
      "expire_date": null
    },
    {
      "name": "てとてキッチン",
      "name_kana": "",
      "business_type": "飲食店営業",
      "address": "富山県内一円",
      "lat": null,
      "lng": null,
      "geocoding_level": null,
      "phone": "",
      "license_no": "221665",
      "license_date": null,
      "expire_date": null
    },
    {
      "name": "ひだくしちゃん",
      "name_kana": "",
      "business_type": "飲食店営業",
      "address": "富山県内一円",
      "lat": null,
      "lng": null,
      "geocoding_level": null,
      "phone": "",
      "license_no": "221684",
      "license_date": null,
      "expire_date": null
    },
    {
      "name": "秋吉移動販売車",
      "name_kana": "",
      "business_type": "飲食店営業",
      "address": "石川県金沢市本江町3-24 富山県内一円",
      "lat": null,
      "lng": null,
      "geocoding_level": null,
      "phone": "",
      "license_no": "221689",
      "license_date": null,
      "expire_date": null
    },
    {
      "name": "ＳＵＮ’Ｓ",
      "name_kana": "",
      "business_type": "飲食店営業",
      "address": "長野県佐久市春日2917-1 富山県内一円",
      "lat": null,
      "lng": null,
      "geocoding_level": null,
      "phone": "",
      "license_no": "221706",
      "license_date": null,
      "expire_date": null
    },
    {
      "name": "ターさんタイ料理",
      "name_kana": "",
      "business_type": "飲食店営業",
      "address": "富山県内一円",
      "lat": null,
      "lng": null,
      "geocoding_level": null,
      "phone": "",
      "license_no": "221717",
      "license_date": null,
      "expire_date": null
    },
    {
      "name": "ピザーラ諏訪店",
      "name_kana": "",
      "business_type": "飲食店営業",
      "address": "富山県内一円",
      "lat": null,
      "lng": null,
      "geocoding_level": null,
      "phone": "",
      "license_no": "221733",
      "license_date": null,
      "expire_date": null
    },
    {
      "name": "Ｆｏｏｄ　ｔｏ　Ｌｕｃｋ",
      "name_kana": "",
      "business_type": "飲食店営業",
      "address": "富山県内一円",
      "lat": null,
      "lng": null,
      "geocoding_level": null,
      "phone": "",
      "license_no": "221743",
      "license_date": null,
      "expire_date": null
    },
    {
      "name": "Ｎａｔｕｒｅｌｉｎｅ　Ｂ．Ｃ．",
      "name_kana": "",
      "business_type": "飲食店営業",
      "address": "富山県内一円",
      "lat": null,
      "lng": null,
      "geocoding_level": null,
      "phone": "",
      "license_no": "221800",
      "license_date": null,
      "expire_date": null
    },
    {
      "name": "ＩＬ　ＧＩＡＲＤＩＮＯ",
      "name_kana": "",
      "business_type": "飲食店営業",
      "address": "石川県加賀市別所町3-29 富山県内一円",
      "lat": null,
      "lng": null,
      "geocoding_level": null,
      "phone": "0761-77-5214",
      "license_no": "221817",
      "license_date": null,
      "expire_date": null
    },
    {
      "name": "麺福食堂",
      "name_kana": "",
      "business_type": "飲食店営業",
      "address": "富山県内一円",
      "lat": null,
      "lng": null,
      "geocoding_level": null,
      "phone": "",
      "license_no": "221824",
      "license_date": null,
      "expire_date": null
    },
    {
      "name": "がじゅん",
      "name_kana": "",
      "business_type": "飲食店営業",
      "address": "石川県河北郡内灘町向栗崎1-152 シルクハイムITO C号 富山県内一円",
      "lat": null,
      "lng": null,
      "geocoding_level": null,
      "phone": "",
      "license_no": "221837",
      "license_date": null,
      "expire_date": null
    },
    {
      "name": "Ｍａｎ　ｄｅ　Ｂａｎａｎａ",
      "name_kana": "",
      "business_type": "飲食店営業",
      "address": "富山県内一円",
      "lat": null,
      "lng": null,
      "geocoding_level": null,
      "phone": "",
      "license_no": "221849",
      "license_date": null,
      "expire_date": null
    },
    {
      "name": "ｕｆｏｔａｂｌｅ　Ｃａｆｅ　Ｔｏ　Ｇｏ",
      "name_kana": "",
      "business_type": "飲食店営業",
      "address": "富山県内一円",
      "lat": null,
      "lng": null,
      "geocoding_level": null,
      "phone": "",
      "license_no": "221916",
      "license_date": null,
      "expire_date": null
    },
    {
      "name": "ヤマグチ",
      "name_kana": "",
      "business_type": "飲食店営業",
      "address": "富山県内一円",
      "lat": null,
      "lng": null,
      "geocoding_level": null,
      "phone": "",
      "license_no": "222002",
      "license_date": null,
      "expire_date": null
    },
    {
      "name": "鯛平楽",
      "name_kana": "",
      "business_type": "飲食店営業",
      "address": "富山県内一円",
      "lat": null,
      "lng": null,
      "geocoding_level": null,
      "phone": "",
      "license_no": "222046",
      "license_date": null,
      "expire_date": null
    },
    {
      "name": "おやつＳＨＯＰリバシー",
      "name_kana": "",
      "business_type": "飲食店営業",
      "address": "富山県内一円",
      "lat": null,
      "lng": null,
      "geocoding_level": null,
      "phone": "",
      "license_no": "222050",
      "license_date": null,
      "expire_date": null
    },
    {
      "name": "ピザ　ＢＵＳ　ＪＯＣＯＶＯ",
      "name_kana": "",
      "business_type": "飲食店営業",
      "address": "石川県河北郡津幡町太田は209-1 富山県内一円",
      "lat": null,
      "lng": null,
      "geocoding_level": null,
      "phone": "",
      "license_no": "222078",
      "license_date": null,
      "expire_date": null
    },
    {
      "name": "いかのおみせ",
      "name_kana": "",
      "business_type": "飲食店営業",
      "address": "富山県内一円",
      "lat": null,
      "lng": null,
      "geocoding_level": null,
      "phone": "",
      "license_no": "230121",
      "license_date": null,
      "expire_date": null
    },
    {
      "name": "宝商店　マカ号３",
      "name_kana": "",
      "business_type": "飲食店営業",
      "address": "富山県内一円",
      "lat": null,
      "lng": null,
      "geocoding_level": null,
      "phone": "",
      "license_no": "230135",
      "license_date": null,
      "expire_date": null
    },
    {
      "name": "ＫＯＭＯ’Ｓ　ＫＩＴＣＨＥＮ",
      "name_kana": "",
      "business_type": "飲食店営業",
      "address": "富山県内一円",
      "lat": null,
      "lng": null,
      "geocoding_level": null,
      "phone": "",
      "license_no": "230218",
      "license_date": null,
      "expire_date": null
    },
    {
      "name": "つくばい亭　キッチンカー",
      "name_kana": "",
      "business_type": "飲食店営業",
      "address": "県内一円",
      "lat": null,
      "lng": null,
      "geocoding_level": null,
      "phone": "0766-82-2981",
      "license_no": "230445",
      "license_date": null,
      "expire_date": null
    },
    {
      "name": "月と兎",
      "name_kana": "",
      "business_type": "飲食店営業",
      "address": "富山県内一円",
      "lat": null,
      "lng": null,
      "geocoding_level": null,
      "phone": "0766-75-8832",
      "license_no": "230471",
      "license_date": null,
      "expire_date": null
    },
    {
      "name": "キッチンカー　Feliz",
      "name_kana": "",
      "business_type": "飲食店営業",
      "address": "富山県内一円",
      "lat": null,
      "lng": null,
      "geocoding_level": null,
      "phone": "",
      "license_no": "230502",
      "license_date": null,
      "expire_date": null
    },
    {
      "name": "ＴＩ－ＤＡ",
      "name_kana": "",
      "business_type": "飲食店営業",
      "address": "富山県内一円",
      "lat": null,
      "lng": null,
      "geocoding_level": null,
      "phone": "",
      "license_no": "230580",
      "license_date": null,
      "expire_date": null
    },
    {
      "name": "モバイルキッチン",
      "name_kana": "",
      "business_type": "飲食店営業",
      "address": "富山県内一円",
      "lat": null,
      "lng": null,
      "geocoding_level": null,
      "phone": "",
      "license_no": "230698",
      "license_date": null,
      "expire_date": null
    },
    {
      "name": "F-TRUCK 112 YO",
      "name_kana": "",
      "business_type": "飲食店営業",
      "address": "富山県内一円",
      "lat": null,
      "lng": null,
      "geocoding_level": null,
      "phone": "",
      "license_no": "230709",
      "license_date": null,
      "expire_date": null
    },
    {
      "name": "とくし丸",
      "name_kana": "",
      "business_type": "乳類販売業",
      "address": "富山県内一円",
      "lat": null,
      "lng": null,
      "geocoding_level": null,
      "phone": "",
      "license_no": "180091",
      "license_date": null,
      "expire_date": null
    },
    {
      "name": "とくし丸",
      "name_kana": "",
      "business_type": "魚介類販売業（包装済の魚介類のみの販売）",
      "address": "富山県内一円",
      "lat": null,
      "lng": null,
      "geocoding_level": null,
      "phone": "",
      "license_no": "180091",
      "license_date": null,
      "expire_date": null
    },
    {
      "name": "とくし丸",
      "name_kana": "",
      "business_type": "食肉販売業（包装済の食肉のみの販売）",
      "address": "富山県内一円",
      "lat": null,
      "lng": null,
      "geocoding_level": null,
      "phone": "",
      "license_no": "180091",
      "license_date": null,
      "expire_date": null
    },
    {
      "name": "イムちゃんフーズ",
      "name_kana": "",
      "business_type": "飲食店営業",
      "address": "富山県内一円",
      "lat": null,
      "lng": null,
      "geocoding_level": null,
      "phone": "",
      "license_no": "230869",
      "license_date": null,
      "expire_date": null
    },
    {
      "name": "カレーハウスＣｏＣｏ壱番屋　移動販売店",
      "name_kana": "",
      "business_type": "飲食店営業",
      "address": "富山県内一円",
      "lat": null,
      "lng": null,
      "geocoding_level": null,
      "phone": "",
      "license_no": "230962",
      "license_date": null,
      "expire_date": null
    },
    {
      "name": "インディラ　CURRY　TRUCK",
      "name_kana": "",
      "business_type": "飲食店営業",
      "address": "富山県内一円",
      "lat": null,
      "lng": null,
      "geocoding_level": null,
      "phone": "0766-55-4977",
      "license_no": "231076",
      "license_date": null,
      "expire_date": null
    },
    {
      "name": "Ｍａｔａｔａｂｉ",
      "name_kana": "",
      "business_type": "飲食店営業",
      "address": "富山県内一円",
      "lat": null,
      "lng": null,
      "geocoding_level": null,
      "phone": "",
      "license_no": "240060",
      "license_date": null,
      "expire_date": null
    },
    {
      "name": "ささら屋立山本店（自動車）",
      "name_kana": "",
      "business_type": "飲食店営業",
      "address": "立山町 富山県内一円",
      "lat": null,
      "lng": null,
      "geocoding_level": null,
      "phone": "076-463-6011",
      "license_no": "240410",
      "license_date": null,
      "expire_date": null
    },
    {
      "name": "TRAILER BAR HAKU",
      "name_kana": "",
      "business_type": "飲食店営業",
      "address": "富山県内一円",
      "lat": null,
      "lng": null,
      "geocoding_level": null,
      "phone": "",
      "license_no": "240490",
      "license_date": null,
      "expire_date": null
    },
    {
      "name": "Ｌｉｆｅｔｉｍｅ　キッチンカー",
      "name_kana": "",
      "business_type": "飲食店営業",
      "address": "立山町 富山県内一円",
      "lat": null,
      "lng": null,
      "geocoding_level": null,
      "phone": "076-461-7411",
      "license_no": "240632",
      "license_date": null,
      "expire_date": null
    },
    {
      "name": "デリアテール株式会社",
      "name_kana": "",
      "business_type": "飲食店営業",
      "address": "富山県内一円",
      "lat": null,
      "lng": null,
      "geocoding_level": null,
      "phone": "0776-52-7725",
      "license_no": "240735",
      "license_date": null,
      "expire_date": null
    },
    {
      "name": "グラフミューラー",
      "name_kana": "",
      "business_type": "飲食店営業",
      "address": "富山県内一円",
      "lat": null,
      "lng": null,
      "geocoding_level": null,
      "phone": "",
      "license_no": "240737",
      "license_date": null,
      "expire_date": null
    },
    {
      "name": "株式会社めん遊館",
      "name_kana": "",
      "business_type": "飲食店営業",
      "address": "福井県越前市真柄町7-37 富山県内一円",
      "lat": null,
      "lng": null,
      "geocoding_level": null,
      "phone": "",
      "license_no": "240759",
      "license_date": null,
      "expire_date": null
    },
    {
      "name": "むすびや",
      "name_kana": "",
      "business_type": "飲食店営業",
      "address": "富山県内一円",
      "lat": null,
      "lng": null,
      "geocoding_level": null,
      "phone": "",
      "license_no": "240791",
      "license_date": null,
      "expire_date": null
    },
    {
      "name": "Ken's Food Truck　2号車",
      "name_kana": "",
      "business_type": "飲食店営業",
      "address": "富山県内一円",
      "lat": null,
      "lng": null,
      "geocoding_level": null,
      "phone": "",
      "license_no": "250033",
      "license_date": null,
      "expire_date": null
    },
    {
      "name": "Ainz cafe",
      "name_kana": "",
      "business_type": "飲食店営業",
      "address": "富山県内一円",
      "lat": null,
      "lng": null,
      "geocoding_level": null,
      "phone": "",
      "license_no": "250105",
      "license_date": null,
      "expire_date": null
    },
    {
      "name": "nosorato by ひらみゆき農園",
      "name_kana": "",
      "business_type": "飲食店営業",
      "address": "富山県内一円",
      "lat": null,
      "lng": null,
      "geocoding_level": null,
      "phone": "",
      "license_no": "250128",
      "license_date": null,
      "expire_date": null
    },
    {
      "name": "BLACK KITCHEN CAR ゆUUUUUめ",
      "name_kana": "",
      "business_type": "飲食店営業",
      "address": "富山県内一円",
      "lat": null,
      "lng": null,
      "geocoding_level": null,
      "phone": "",
      "license_no": "250134",
      "license_date": null,
      "expire_date": null
    },
    {
      "name": "Ｃａｆｅアルモンデ・メデル",
      "name_kana": "",
      "business_type": "飲食店営業",
      "address": "舟橋村 富山県内一円",
      "lat": null,
      "lng": null,
      "geocoding_level": null,
      "phone": "",
      "license_no": "250150",
      "license_date": null,
      "expire_date": null
    },
    {
      "name": "肉はともだち　2号車",
      "name_kana": "",
      "business_type": "飲食店営業",
      "address": "富山県一円",
      "lat": null,
      "lng": null,
      "geocoding_level": null,
      "phone": "",
      "license_no": "250173",
      "license_date": null,
      "expire_date": null
    },
    {
      "name": "xin Chao",
      "name_kana": "",
      "business_type": "飲食店営業",
      "address": "富山県内一円",
      "lat": null,
      "lng": null,
      "geocoding_level": null,
      "phone": "",
      "license_no": "250196",
      "license_date": null,
      "expire_date": null
    },
    {
      "name": "PECONICO DINER",
      "name_kana": "",
      "business_type": "飲食店営業",
      "address": "富山県内一円",
      "lat": null,
      "lng": null,
      "geocoding_level": null,
      "phone": "",
      "license_no": "250329",
      "license_date": null,
      "expire_date": null
    },
    {
      "name": "みぃのぷれすきっちん",
      "name_kana": "",
      "business_type": "飲食店営業",
      "address": "富山県内一円",
      "lat": null,
      "lng": null,
      "geocoding_level": null,
      "phone": "",
      "license_no": "250434",
      "license_date": null,
      "expire_date": null
    },
    {
      "name": "萬屋おてる",
      "name_kana": "",
      "business_type": "飲食店営業",
      "address": "富山県内一円",
      "lat": null,
      "lng": null,
      "geocoding_level": null,
      "phone": "",
      "license_no": "250435",
      "license_date": null,
      "expire_date": null
    },
    {
      "name": "ミーロザスイーツ",
      "name_kana": "",
      "business_type": "飲食店営業",
      "address": "富山県内一円",
      "lat": null,
      "lng": null,
      "geocoding_level": null,
      "phone": "",
      "license_no": "250469",
      "license_date": null,
      "expire_date": null
    },
    {
      "name": "炭火焼鳥　鶏うま",
      "name_kana": "",
      "business_type": "飲食店営業",
      "address": "富山県内一円",
      "lat": null,
      "lng": null,
      "geocoding_level": null,
      "phone": "",
      "license_no": "250470",
      "license_date": null,
      "expire_date": null
    },
    {
      "name": "音cafe",
      "name_kana": "",
      "business_type": "飲食店営業",
      "address": "富山県内一円",
      "lat": null,
      "lng": null,
      "geocoding_level": null,
      "phone": "",
      "license_no": "250477",
      "license_date": null,
      "expire_date": null
    },
    {
      "name": "いざわ商店",
      "name_kana": "",
      "business_type": "飲食店営業",
      "address": "富山県内一円",
      "lat": null,
      "lng": null,
      "geocoding_level": null,
      "phone": "",
      "license_no": "250540",
      "license_date": null,
      "expire_date": null
    },
    {
      "name": "フレッシュフーズストアーキタカワ",
      "name_kana": "",
      "business_type": "飲食店営業",
      "address": "富山県内一円",
      "lat": null,
      "lng": null,
      "geocoding_level": null,
      "phone": "",
      "license_no": "250565",
      "license_date": null,
      "expire_date": null
    },
    {
      "name": "NOTO　NOMAD",
      "name_kana": "",
      "business_type": "飲食店営業",
      "address": "富山県内一円",
      "lat": null,
      "lng": null,
      "geocoding_level": null,
      "phone": "",
      "license_no": "250572",
      "license_date": null,
      "expire_date": null
    },
    {
      "name": "やきやきや　ハマヤ",
      "name_kana": "",
      "business_type": "飲食店営業",
      "address": "富山県内一円",
      "lat": null,
      "lng": null,
      "geocoding_level": null,
      "phone": "",
      "license_no": "250641",
      "license_date": null,
      "expire_date": null
    },
    {
      "name": "アトリエ菓子工房ラグリシーヌ",
      "name_kana": "",
      "business_type": "飲食店営業",
      "address": "富山県内一円",
      "lat": null,
      "lng": null,
      "geocoding_level": null,
      "phone": "",
      "license_no": "230503",
      "license_date": null,
      "expire_date": null
    },
    {
      "name": "ＳＨＩＲＯ",
      "name_kana": "",
      "business_type": "その他の食料・飲料販売業",
      "address": "新潟県糸魚川市東寺町3-1-34",
      "lat": null,
      "lng": null,
      "geocoding_level": null,
      "phone": "",
      "license_no": "250664",
      "license_date": null,
      "expire_date": null
    },
    {
      "name": "串滿斎やきとり家竹松",
      "name_kana": "",
      "business_type": "飲食店営業",
      "address": "富山県内一円",
      "lat": null,
      "lng": null,
      "geocoding_level": null,
      "phone": "",
      "license_no": "250682",
      "license_date": null,
      "expire_date": null
    },
    {
      "name": "世界の山ちゃん　キッチンカー４号車",
      "name_kana": "",
      "business_type": "飲食店営業",
      "address": "富山県内一円",
      "lat": null,
      "lng": null,
      "geocoding_level": null,
      "phone": "052-259-2782",
      "license_no": "250698",
      "license_date": null,
      "expire_date": null
    },
    {
      "name": "ＲＡＫＵ　ＣＡＦＥ",
      "name_kana": "",
      "business_type": "飲食店営業",
      "address": "富山県内一円",
      "lat": null,
      "lng": null,
      "geocoding_level": null,
      "phone": "",
      "license_no": "250705",
      "license_date": null,
      "expire_date": null
    },
    {
      "name": "チャンピオンカレー　FOODTRUCK",
      "name_kana": "",
      "business_type": "飲食店営業",
      "address": "富山県内一円",
      "lat": null,
      "lng": null,
      "geocoding_level": null,
      "phone": "",
      "license_no": "250797",
      "license_date": null,
      "expire_date": null
    },
    {
      "name": "デリスター２",
      "name_kana": "",
      "business_type": "飲食店営業",
      "address": "富山県内一円",
      "lat": null,
      "lng": null,
      "geocoding_level": null,
      "phone": "",
      "license_no": "250818",
      "license_date": null,
      "expire_date": null
    },
    {
      "name": "やきとり竜鳳　宇都宮880あ2289",
      "name_kana": "",
      "business_type": "飲食店営業",
      "address": "富山県内一円",
      "lat": null,
      "lng": null,
      "geocoding_level": null,
      "phone": "076-225-3142",
      "license_no": "250855",
      "license_date": null,
      "expire_date": null
    },
    {
      "name": "Ｌａｔ",
      "name_kana": "",
      "business_type": "飲食店営業",
      "address": "富山県内一円",
      "lat": null,
      "lng": null,
      "geocoding_level": null,
      "phone": "",
      "license_no": "250910",
      "license_date": null,
      "expire_date": null
    },
    {
      "name": "珈琲所コメダ珈琲店　キッチンカー",
      "name_kana": "",
      "business_type": "飲食店営業",
      "address": "富山県内一円",
      "lat": null,
      "lng": null,
      "geocoding_level": null,
      "phone": "",
      "license_no": "260194",
      "license_date": null,
      "expire_date": null
    },
    {
      "name": "Ｒｅｐｏｓ　ルポ",
      "name_kana": "",
      "business_type": "飲食店営業",
      "address": "富山県内一円",
      "lat": null,
      "lng": null,
      "geocoding_level": null,
      "phone": "",
      "license_no": "260219",
      "license_date": null,
      "expire_date": null
    },
    {
      "name": "しゅんちゃん野菜",
      "name_kana": "",
      "business_type": "飲食店営業",
      "address": "富山県内一円",
      "lat": null,
      "lng": null,
      "geocoding_level": null,
      "phone": "",
      "license_no": "260294",
      "license_date": null,
      "expire_date": null
    },
    {
      "name": "１４ＫＩＴＣＨＥＮ",
      "name_kana": "",
      "business_type": "飲食店営業",
      "address": "富山県内一円",
      "lat": null,
      "lng": null,
      "geocoding_level": null,
      "phone": "0763-77-4689",
      "license_no": "260335",
      "license_date": null,
      "expire_date": null
    },
    {
      "name": "珈琲と、エトセトラ",
      "name_kana": "",
      "business_type": "飲食店営業",
      "address": "富山県内一円",
      "lat": null,
      "lng": null,
      "geocoding_level": null,
      "phone": "",
      "license_no": "260486",
      "license_date": null,
      "expire_date": null
    }
  ]
}
