{
  "meta": {
    "updated": 1782280239
  },
  "data": [
    {
      "name": "ローソン読谷波平店",
      "name_kana": "",
      "business_type": "食肉販売業",
      "address": "読谷村波平大当原２１５８－１",
      "lat": null,
      "lng": null,
      "phone": "",
      "license_no": "第03201401155号",
      "license_date": "2014-09-11",
      "expire_date": "2021-09-30"
    },
    {
      "name": "ファミリーマート読谷長浜店",
      "name_kana": "",
      "business_type": "食肉販売業",
      "address": "読谷村長浜１６２９－１",
      "lat": null,
      "lng": null,
      "phone": "",
      "license_no": "第03201401224号",
      "license_date": "2014-09-19",
      "expire_date": "2021-09-30"
    },
    {
      "name": "ファミリーマート読谷トリイステーション前店",
      "name_kana": "",
      "business_type": "食肉販売業",
      "address": "読谷村楚辺１１７９",
      "lat": null,
      "lng": null,
      "phone": "",
      "license_no": "第03201401226号",
      "license_date": "2014-09-19",
      "expire_date": "2021-09-30"
    },
    {
      "name": "ファミリーマート読谷伊良皆店",
      "name_kana": "",
      "business_type": "食肉販売業",
      "address": "読谷村伊良皆１３５－１",
      "lat": null,
      "lng": null,
      "phone": "",
      "license_no": "第03201401342号",
      "license_date": "2014-09-29",
      "expire_date": "2021-09-30"
    },
    {
      "name": "ファミリーマートＦＣ読谷とや店",
      "name_kana": "",
      "business_type": "食肉販売業",
      "address": "読谷村都屋２６３－１",
      "lat": null,
      "lng": null,
      "phone": "",
      "license_no": "第03201401384号",
      "license_date": "2014-09-30",
      "expire_date": "2021-09-30"
    },
    {
      "name": "ファミリーマートＦＣ読谷座喜味店",
      "name_kana": "",
      "business_type": "食肉販売業",
      "address": "読谷村座喜味５６９",
      "lat": null,
      "lng": null,
      "phone": "",
      "license_no": "第03201401397号",
      "license_date": "2014-10-01",
      "expire_date": "2021-10-31"
    },
    {
      "name": "ファミリーマート読谷古堅店",
      "name_kana": "",
      "business_type": "食肉販売業",
      "address": "読谷村古堅６５４－１",
      "lat": null,
      "lng": null,
      "phone": "",
      "license_no": "第03201401437号",
      "license_date": "2014-10-06",
      "expire_date": "2021-10-31"
    },
    {
      "name": "オカゲサマ製麺食堂",
      "name_kana": "",
      "business_type": "食肉販売業",
      "address": "読谷村大木３２６－６",
      "lat": null,
      "lng": null,
      "phone": "",
      "license_no": "第03201600438号",
      "license_date": "2016-06-13",
      "expire_date": "2022-06-30"
    },
    {
      "name": "知念冷凍食品",
      "name_kana": "",
      "business_type": "食肉販売業",
      "address": "読谷村喜名２３４６－１１",
      "lat": null,
      "lng": null,
      "phone": "",
      "license_no": "第03201600974号",
      "license_date": "2016-08-10",
      "expire_date": "2022-08-31"
    },
    {
      "name": "（株）丸大　　伊良皆店",
      "name_kana": "",
      "business_type": "食肉販売業",
      "address": "読谷村伊良皆３０２",
      "lat": null,
      "lng": null,
      "phone": "",
      "license_no": "第03201601074号",
      "license_date": "2016-08-29",
      "expire_date": "2022-08-31"
    },
    {
      "name": "ファミリーマート読谷トリイステーション前店",
      "name_kana": "",
      "business_type": "食肉販売業",
      "address": "読谷村楚辺１１７９",
      "lat": null,
      "lng": null,
      "phone": "",
      "license_no": "第03201601585号",
      "license_date": "2016-10-25",
      "expire_date": "2022-10-31"
    },
    {
      "name": "読谷ファーマーズマーケット",
      "name_kana": "",
      "business_type": "食肉販売業",
      "address": "読谷村喜名２３４６－１１",
      "lat": null,
      "lng": null,
      "phone": "",
      "license_no": "第03201602630号",
      "license_date": "2017-03-31",
      "expire_date": "2023-03-31"
    },
    {
      "name": "ローソン読谷長浜店",
      "name_kana": "",
      "business_type": "食肉販売業",
      "address": "読谷村長浜１０９２－１",
      "lat": null,
      "lng": null,
      "phone": "",
      "license_no": "第03201700679号",
      "license_date": "2017-07-20",
      "expire_date": "2023-07-31"
    },
    {
      "name": "大湾シティ　精肉作業場",
      "name_kana": "",
      "business_type": "食肉販売業",
      "address": "読谷村大湾３４３",
      "lat": null,
      "lng": null,
      "phone": "",
      "license_no": "第03201700685号",
      "license_date": "2017-07-20",
      "expire_date": "2023-07-31"
    },
    {
      "name": "山城精肉店",
      "name_kana": "",
      "business_type": "食肉販売業",
      "address": "読谷村伊良皆２６７",
      "lat": null,
      "lng": null,
      "phone": "",
      "license_no": "第03201700825号",
      "license_date": "2017-08-07",
      "expire_date": "2023-08-31"
    },
    {
      "name": "サンマート喜名店",
      "name_kana": "",
      "business_type": "食肉販売業",
      "address": "読谷村喜名２２２４－３",
      "lat": null,
      "lng": null,
      "phone": "",
      "license_no": "第03201700955号",
      "license_date": "2017-08-31",
      "expire_date": "2023-08-31"
    },
    {
      "name": "ダイレックス読谷店",
      "name_kana": "",
      "business_type": "食肉販売業",
      "address": "読谷村大湾４１",
      "lat": null,
      "lng": null,
      "phone": "",
      "license_no": "第03201701627号",
      "license_date": "2017-11-28",
      "expire_date": "2024-11-30"
    },
    {
      "name": "農業生産法人株式会社ＮＩＫＵＹＡ",
      "name_kana": "",
      "business_type": "食肉販売業",
      "address": "読谷村伊良皆１２６ （１Ｆ）",
      "lat": null,
      "lng": null,
      "phone": "",
      "license_no": "第03201800082号",
      "license_date": "2018-04-16",
      "expire_date": "2024-04-30"
    },
    {
      "name": "中川牧場（中川ミート）",
      "name_kana": "",
      "business_type": "食肉販売業",
      "address": "読谷村渡具知６１５－１",
      "lat": null,
      "lng": null,
      "phone": "",
      "license_no": "第03201800762号",
      "license_date": "2018-07-26",
      "expire_date": "2024-07-31"
    },
    {
      "name": "ドラッグストアモリ　読谷店",
      "name_kana": "",
      "business_type": "食肉販売業",
      "address": "読谷村比謝４９１－１",
      "lat": null,
      "lng": null,
      "phone": "",
      "license_no": "第03201801463号",
      "license_date": "2018-11-01",
      "expire_date": "2025-11-30"
    },
    {
      "name": "沖縄ハム総合食品株式会社",
      "name_kana": "",
      "business_type": "食肉販売業",
      "address": "読谷村座喜味２８２２－３",
      "lat": null,
      "lng": null,
      "phone": "",
      "license_no": "第03201801842号",
      "license_date": "2018-12-27",
      "expire_date": "2025-01-31"
    },
    {
      "name": "ザ・ビッグ都屋店",
      "name_kana": "",
      "business_type": "食肉販売業",
      "address": "読谷村座喜味３１７１",
      "lat": null,
      "lng": null,
      "phone": "",
      "license_no": "第03201801928号",
      "license_date": "2019-01-21",
      "expire_date": "2025-01-31"
    },
    {
      "name": "波平食品",
      "name_kana": "",
      "business_type": "食肉販売業",
      "address": "読谷村喜名２２５－１",
      "lat": null,
      "lng": null,
      "phone": "",
      "license_no": "第03201802264号",
      "license_date": "2019-02-26",
      "expire_date": "2025-02-28"
    },
    {
      "name": "タウンプラザかねひで　読谷店",
      "name_kana": "",
      "business_type": "食肉販売業",
      "address": "読谷村波平２１６１－２",
      "lat": null,
      "lng": null,
      "phone": "",
      "license_no": "第03201802387号",
      "license_date": "2019-03-15",
      "expire_date": "2025-03-31"
    },
    {
      "name": "Ｖ２１食品館　楚辺店",
      "name_kana": "",
      "business_type": "食肉販売業",
      "address": "読谷村楚辺１２７９－１３",
      "lat": null,
      "lng": null,
      "phone": "",
      "license_no": "第03201900419号",
      "license_date": "2019-06-03",
      "expire_date": "2025-06-30"
    },
    {
      "name": "ヨナハ鮮魚店",
      "name_kana": "",
      "business_type": "食肉販売業",
      "address": "読谷村渡慶次１０６",
      "lat": null,
      "lng": null,
      "phone": "",
      "license_no": "第03201900773号",
      "license_date": "2019-07-18",
      "expire_date": "2025-07-31"
    },
    {
      "name": "マルクニスーパー",
      "name_kana": "",
      "business_type": "食肉販売業",
      "address": "読谷村渡慶次１４６",
      "lat": null,
      "lng": null,
      "phone": "",
      "license_no": "第03201901013号",
      "license_date": "2019-08-29",
      "expire_date": "2026-08-31"
    },
    {
      "name": "（株）丸大　波平店",
      "name_kana": "",
      "business_type": "食肉販売業",
      "address": "読谷村波平１６９６",
      "lat": null,
      "lng": null,
      "phone": "",
      "license_no": "第03201901289号",
      "license_date": "2019-10-04",
      "expire_date": "2025-10-31"
    },
    {
      "name": "池城ストアー",
      "name_kana": "",
      "business_type": "食肉販売業",
      "address": "読谷村喜名４７８",
      "lat": null,
      "lng": null,
      "phone": "",
      "license_no": "第03201901694号",
      "license_date": "2019-11-21",
      "expire_date": "2025-11-30"
    },
    {
      "name": "にくや　精肉店",
      "name_kana": "",
      "business_type": "食肉販売業",
      "address": "読谷村都屋２５７ （１階）",
      "lat": null,
      "lng": null,
      "phone": "",
      "license_no": "第03201901901号",
      "license_date": "2019-12-18",
      "expire_date": "2027-01-31"
    },
    {
      "name": "沖縄ハム総合食品㈱読谷工場",
      "name_kana": "",
      "business_type": "食肉販売業",
      "address": "読谷村座喜味２８２２－３",
      "lat": null,
      "lng": null,
      "phone": "",
      "license_no": "第03201902407号",
      "license_date": "2020-02-28",
      "expire_date": "2026-02-28"
    },
    {
      "name": "知花冷凍所",
      "name_kana": "",
      "business_type": "食肉販売業",
      "address": "読谷村高志保４７",
      "lat": null,
      "lng": null,
      "phone": "",
      "license_no": "第03201902429号",
      "license_date": "2020-03-04",
      "expire_date": "2026-03-31"
    },
    {
      "name": "マックスバリュ読谷店",
      "name_kana": "",
      "business_type": "食肉販売業",
      "address": "読谷村古堅７４０",
      "lat": null,
      "lng": null,
      "phone": "",
      "license_no": "第03202000204号",
      "license_date": "2020-04-28",
      "expire_date": "2026-04-30"
    },
    {
      "name": "ローソン読谷座喜味店",
      "name_kana": "",
      "business_type": "食肉販売業",
      "address": "読谷村座喜味２０１２－１",
      "lat": null,
      "lng": null,
      "phone": "",
      "license_no": "第03202000237号",
      "license_date": "2020-05-08",
      "expire_date": "2027-05-31"
    },
    {
      "name": "マックスバリュ座喜味店",
      "name_kana": "",
      "business_type": "食肉販売業",
      "address": "読谷村上地２０５－１",
      "lat": null,
      "lng": null,
      "phone": "",
      "license_no": "第03202000291号",
      "license_date": "2020-05-12",
      "expire_date": "2026-05-31"
    },
    {
      "name": "あらん家",
      "name_kana": "",
      "business_type": "食肉販売業",
      "address": "読谷村伊良皆３１３－３",
      "lat": null,
      "lng": null,
      "phone": "",
      "license_no": "第03202000408号",
      "license_date": "2020-05-21",
      "expire_date": "2026-05-31"
    },
    {
      "name": "ざきみ弁当",
      "name_kana": "",
      "business_type": "食肉販売業",
      "address": "読谷村座喜味１４１－２",
      "lat": null,
      "lng": null,
      "phone": "",
      "license_no": "第03202000412号",
      "license_date": "2020-05-21",
      "expire_date": "2026-05-31"
    },
    {
      "name": "まつだ商会",
      "name_kana": "",
      "business_type": "食肉販売業",
      "address": "読谷村高志保３００",
      "lat": null,
      "lng": null,
      "phone": "",
      "license_no": "第03202000710号",
      "license_date": "2020-07-01",
      "expire_date": "2026-07-31"
    },
    {
      "name": "おきなわポークビレッジ",
      "name_kana": "",
      "business_type": "食肉販売業",
      "address": "読谷村渡具知２２８",
      "lat": null,
      "lng": null,
      "phone": "",
      "license_no": "第03202000782号",
      "license_date": "2020-04-30",
      "expire_date": "2026-04-30"
    },
    {
      "name": "焼肉五苑　読谷店",
      "name_kana": "",
      "business_type": "食肉販売業",
      "address": "読谷村大湾３５９－１",
      "lat": null,
      "lng": null,
      "phone": "",
      "license_no": "第03202000839号",
      "license_date": "2020-07-16",
      "expire_date": "2026-07-31"
    },
    {
      "name": "（有）トップフーズ",
      "name_kana": "",
      "business_type": "食肉販売業",
      "address": "読谷村楚辺２３４７－１",
      "lat": null,
      "lng": null,
      "phone": "",
      "license_no": "第03202001557号",
      "license_date": "2020-11-12",
      "expire_date": "2026-11-30"
    },
    {
      "name": "ローソン読谷大湾店",
      "name_kana": "",
      "business_type": "食肉販売業",
      "address": "読谷村比謝長佐久原５０５－１ （仮換地１街区１画区）",
      "lat": null,
      "lng": null,
      "phone": "",
      "license_no": "第03202001638号",
      "license_date": "2020-11-26",
      "expire_date": "2026-11-30"
    },
    {
      "name": "ヨギ精肉店",
      "name_kana": "",
      "business_type": "食肉販売業",
      "address": "読谷村座喜味１８９３　１Ｆ",
      "lat": null,
      "lng": null,
      "phone": "",
      "license_no": "第03202002205号",
      "license_date": "2021-02-10",
      "expire_date": "2027-02-28"
    },
    {
      "name": "セブン－イレブン読谷波平店",
      "name_kana": "",
      "business_type": "食肉販売業",
      "address": "読谷村波平８４５－２",
      "lat": null,
      "lng": null,
      "phone": "",
      "license_no": "第03202002280号",
      "license_date": "2021-02-19",
      "expire_date": "2028-02-29"
    },
    {
      "name": "黒猫屋　読谷店",
      "name_kana": "",
      "business_type": "食肉販売業",
      "address": "読谷村都屋２６３－１",
      "lat": null,
      "lng": null,
      "phone": "",
      "license_no": "第03202100351号",
      "license_date": "2021-05-13",
      "expire_date": "2027-05-31"
    }
  ]
}
